LICENSE
MANIFEST.in
README.rst
setup.py
django_gearman_proxy/__init__.py
django_gearman_proxy/models.py
django_gearman_proxy/settings.py
django_gearman_proxy.egg-info/PKG-INFO
django_gearman_proxy.egg-info/SOURCES.txt
django_gearman_proxy.egg-info/dependency_links.txt
django_gearman_proxy.egg-info/requires.txt
django_gearman_proxy.egg-info/top_level.txt
django_gearman_proxy/backends/__init__.py
django_gearman_proxy/backends/mail.py
django_gearman_proxy/backends/sms.py
django_gearman_proxy/management/__init__.py
django_gearman_proxy/management/commands/__init__.py
django_gearman_proxy/management/commands/send_mail.py
django_gearman_proxy/management/commands/send_sms.py
django_gearman_proxy/serializers/__init__.py
django_gearman_proxy/serializers/mail/__init__.py
django_gearman_proxy/serializers/mail/json.py
django_gearman_proxy/serializers/sms/__init__.py
django_gearman_proxy/serializers/sms/json.py
django_gearman_proxy/tests/__init__.py
django_gearman_proxy/tests/backends/__init__.py
django_gearman_proxy/tests/backends/test_mail.py
django_gearman_proxy/tests/backends/test_sms.py
django_gearman_proxy/tests/management/__init__.py
django_gearman_proxy/tests/management/commands/__init__.py
django_gearman_proxy/tests/management/commands/test_send_mail.py
django_gearman_proxy/tests/management/commands/test_send_sms.py
django_gearman_proxy/tests/serializers/__init__.py
django_gearman_proxy/tests/serializers/mail/__init__.py
django_gearman_proxy/tests/serializers/mail/test_json.py
django_gearman_proxy/tests/serializers/sms/__init__.py
django_gearman_proxy/tests/serializers/sms/test_json.py