Metadata-Version: 1.1
Name: django-gearman-proxy
Version: 1.0.1
Summary: Proxy backends/workers for asynchronous email and sms sending using gearman as message queue.
Home-page: http://www.codescale.net/en/community#django-gearman-proxy
Author: Vladimír Gorej
Author-email: gorej@codescale.net
License: BSD
Download-URL: http://github.com/codescaleinc/django-gearman-proxy/tarball/master
Keywords: django gearman email sms asynchronous message queue
Platform: any
Classifier: Development Status :: 5 - Production/Stable
Classifier: Environment :: Web Environment
Classifier: Intended Audience :: Developers
Classifier: Intended Audience :: Information Technology
Classifier: License :: OSI Approved :: BSD License
Classifier: Operating System :: OS Independent
Classifier: Programming Language :: Python
Classifier: Topic :: Utilities
Classifier: Topic :: Internet :: WWW/HTTP
